UDlextag2json.py
conllulex2UDlextag.py
conllulex2csv.py
conllulex2json.py
csv2conllulex.py
govobj.py
json2conllulex.py
lexcatter.py
mwerender.py
normalize_mwe_numbering.py
psseval.py
streuseval.py
streusvis.py
supdate.py
supersenses.py
tagging.py
tquery.py
tupdate.py
streusle-4.5.dist-info/LICENSE.txt
streusle-4.5.dist-info/METADATA
streusle-4.5.dist-info/WHEEL
streusle-4.5.dist-info/top_level.txt
streusle-4.5.dist-info/RECORD
