Metadata-Version: 2.1
Name: streusle
Version: 4.5
Summary: STREUSLE: a corpus with comprehensive lexical semantic annotation (multiword expressions, supersenses)
Home-page: https://github.com/nert-nlp/streusle
Author: Nathan Schneider
Author-email: nathan.schneider@georgetown.edu
Classifier: Programming Language :: Python :: 3
Classifier: Operating System :: OS Independent
License-File: LICENSE.txt
